boyle/__init__.py
boyle/commands.py
boyle/config.py
boyle/databuffer.py
boyle/excel_utils.py
boyle/exceptions.py
boyle/hdf5.py
boyle/ipynb.py
boyle/more_collections.py
boyle/parallel.py
boyle/petitdb.py
boyle/storage.py
boyle/version.py
boyle/dicom/__init__.py
boyle/dicom/comparison.py
boyle/dicom/convert.py
boyle/dicom/itertools.py
boyle/dicom/sets.py
boyle/dicom/utils.py
boyle/files/__init__.py
boyle/files/configuration.py
boyle/files/file_tree_map.py
boyle/files/names.py
boyle/files/search.py
boyle/files/utils.py
boyle/image/__init__.py
boyle/image/base.py
boyle/image/utils.py
boyle/mha/__init__.py
boyle/mha/check.py
boyle/mha/mha.py
boyle/mha/read.py
boyle/mha/tags.py
boyle/mha/write.py
boyle/mhd/__init__.py
boyle/mhd/check.py
boyle/mhd/read.py
boyle/mhd/tags.py
boyle/mhd/write.py
boyle/nifti/__init__.py
boyle/nifti/check.py
boyle/nifti/coord_transform.py
boyle/nifti/cpac_helpers.py
boyle/nifti/mask.py
boyle/nifti/read.py
boyle/nifti/roi.py
boyle/nifti/sets.py
boyle/nifti/smooth.py
boyle/nifti/storage.py
boyle/nifti/utils.py
boyle/utils/__init__.py
boyle/utils/cache_mixin.py
boyle/utils/compat.py
boyle/utils/imports.py
boyle/utils/logger.py
boyle/utils/numpy_conversions.py
boyle/utils/printable.py
boyle/utils/rcfile.py
boyle/utils/strings.py
boyle/utils/text_files.py
boyle/utils/validation.py
boyle-0.2.0.data/scripts/compare_id_sets.py
boyle-0.2.0.data/scripts/convert_sav.py
boyle-0.2.0.data/scripts/drain_rois
boyle-0.2.0.data/scripts/filetree.py
boyle-0.2.0.data/scripts/split_rois
boyle-0.2.0.dist-info/DESCRIPTION.rst
boyle-0.2.0.dist-info/METADATA
boyle-0.2.0.dist-info/RECORD
boyle-0.2.0.dist-info/WHEEL
boyle-0.2.0.dist-info/metadata.json
boyle-0.2.0.dist-info/top_level.txt
